odoo/addons/l10n_es_toponyms/README.rst
odoo/addons/l10n_es_toponyms/__init__.py
odoo/addons/l10n_es_toponyms/__manifest__.py
odoo/addons/l10n_es_toponyms/gen_src/README.md
odoo/addons/l10n_es_toponyms/gen_src/gen_toponyms_geonames.py
odoo/addons/l10n_es_toponyms/i18n/bg.po
odoo/addons/l10n_es_toponyms/i18n/ca.po
odoo/addons/l10n_es_toponyms/i18n/cs.po
odoo/addons/l10n_es_toponyms/i18n/de.po
odoo/addons/l10n_es_toponyms/i18n/es.po
odoo/addons/l10n_es_toponyms/i18n/es_CO.po
odoo/addons/l10n_es_toponyms/i18n/es_CR.po
odoo/addons/l10n_es_toponyms/i18n/es_ES.po
odoo/addons/l10n_es_toponyms/i18n/eu.po
odoo/addons/l10n_es_toponyms/i18n/fr.po
odoo/addons/l10n_es_toponyms/i18n/gl.po
odoo/addons/l10n_es_toponyms/i18n/hr.po
odoo/addons/l10n_es_toponyms/i18n/l10n_es_toponyms.pot
odoo/addons/l10n_es_toponyms/i18n/nl.po
odoo/addons/l10n_es_toponyms/i18n/pl.po
odoo/addons/l10n_es_toponyms/i18n/pt.po
odoo/addons/l10n_es_toponyms/i18n/pt_BR.po
odoo/addons/l10n_es_toponyms/i18n/ru.po
odoo/addons/l10n_es_toponyms/i18n/sl.po
odoo/addons/l10n_es_toponyms/i18n/sv.po
odoo/addons/l10n_es_toponyms/i18n/tr.po
odoo/addons/l10n_es_toponyms/i18n/vi.po
odoo/addons/l10n_es_toponyms/images/l10n_es_toponyms_config.png
odoo/addons/l10n_es_toponyms/static/description/icon.png
odoo/addons/l10n_es_toponyms/static/description/icon.svg
odoo/addons/l10n_es_toponyms/tests/__init__.py
odoo/addons/l10n_es_toponyms/tests/test_l10n_es_toponyms.py
odoo/addons/l10n_es_toponyms/wizard/__init__.py
odoo/addons/l10n_es_toponyms/wizard/geonames_import.py
odoo/addons/l10n_es_toponyms/wizard/l10n_es_toponyms_wizard.py
odoo/addons/l10n_es_toponyms/wizard/l10n_es_toponyms_wizard.xml
odoo/addons/l10n_es_toponyms/wizard/l10n_es_toponyms_zipcodes.xml
odoo11_addon_l10n_es_toponyms-11.0.1.0.1.dist-info/METADATA
odoo11_addon_l10n_es_toponyms-11.0.1.0.1.dist-info/WHEEL
odoo11_addon_l10n_es_toponyms-11.0.1.0.1.dist-info/top_level.txt
odoo11_addon_l10n_es_toponyms-11.0.1.0.1.dist-info/RECORD
